[
  {
    "indidentId": "691e54cf5b4b2353878f9127",
    "words": [
      {
        "word": "on",
        "count": 0.07410797215372183
      },
      {
        "word": "y",
        "count": 0.07410797215372183
      },
      {
        "word": "est",
        "count": 0.07410797215372183
      },
      {
        "word": "encore",
        "count": 0.07410797215372183
      },
      {
        "word": "avenue",
        "count": 0.07410797215372183
      },
      {
        "word": "du",
        "count": 0.07410797215372183
      },
      {
        "word": "roi",
        "count": 0.07410797215372183
      },
      {
        "word": "albert",
        "count": 0.07410797215372183
      },
      {
        "word": "1340",
        "count": 0.07410797215372183
      },
      {
        "word": "ottignies",
        "count": 0.07410797215372183
      },
      {
        "word": "louvain",
        "count": 0.07410797215372183
      },
      {
        "word": "la",
        "count": 0.07410797215372183
      },
      {
        "word": "neuve",
        "count": 0.07410797215372183
      }
    ],
    "list": [
      "on",
      "y",
      "est",
      "encore",
      "avenue",
      "du",
      "roi",
      "albert",
      "1340",
      "ottignies",
      "louvain",
      "la",
      "neuve"
    ]
  },
  {
    "indidentId": "691e5b0f6440a8540846d6c8",
    "words": [
      {
        "word": "je",
        "count": 0.05129329438755048
      },
      {
        "word": "regarde",
        "count": 0.05129329438755048
      },
      {
        "word": "si",
        "count": 0.05129329438755048
      },
      {
        "word": "le",
        "count": 0.05129329438755048
      },
      {
        "word": "nom",
        "count": 0.05129329438755048
      },
      {
        "word": "d",
        "count": 0.05129329438755048
      },
      {
        "word": "utilisateur",
        "count": 0.05129329438755048
      },
      {
        "word": "sera",
        "count": 0.05129329438755048
      },
      {
        "word": "affich",
        "count": 0.05129329438755048
      },
      {
        "word": "avenue",
        "count": 0.05129329438755048
      },
      {
        "word": "du",
        "count": 0.05129329438755048
      },
      {
        "word": "roi",
        "count": 0.05129329438755048
      },
      {
        "word": "albert",
        "count": 0.05129329438755048
      },
      {
        "word": "40",
        "count": 0.05129329438755048
      },
      {
        "word": "1340",
        "count": 0.05129329438755048
      },
      {
        "word": "ottignies",
        "count": 0.05129329438755048
      },
      {
        "word": "louvain",
        "count": 0.05129329438755048
      },
      {
        "word": "la",
        "count": 0.05129329438755048
      },
      {
        "word": "neuve",
        "count": 0.05129329438755048
      }
    ],
    "list": [
      "je",
      "regarde",
      "si",
      "le",
      "nom",
      "d",
      "utilisateur",
      "sera",
      "affich",
      "avenue",
      "du",
      "roi",
      "albert",
      "40",
      "1340",
      "ottignies",
      "louvain",
      "la",
      "neuve"
    ]
  }
]